spline_based_transformer/__init__.py
spline_based_transformer/spline_based_transformer.py
spline_based_transformer-0.0.14.dist-info/LICENSE
spline_based_transformer-0.0.14.dist-info/METADATA
spline_based_transformer-0.0.14.dist-info/WHEEL
spline_based_transformer-0.0.14.dist-info/top_level.txt
spline_based_transformer-0.0.14.dist-info/RECORD
