Metadata-Version: 2.1
Name: spline-based-transformer
Version: 0.0.14
Summary: Spline Based Transformer
Author-email: Phil Wang <lucidrains@gmail.com>
License: MIT License
Project-URL: Homepage, https://pypi.org/project/spline-based-transformer
Project-URL: Repository, https://github.com/lucidrains/spline-based-transformer
Keywords: artificial intelligence,deep learning,transformers,attention mechanism,b-spline,latent trajectories
Classifier: Development Status :: 4 - Beta
Classifier: Intended Audience :: Developers
Classifier: Topic :: Scientific/Engineering :: Artificial Intelligence
Classifier: License :: OSI Approved :: MIT License
Classifier: Programming Language :: Python :: 3.8
Requires-Python: >=3.8
License-File: LICENSE
Requires-Dist: einops >=0.8.0
Requires-Dist: torch >=2.2
Requires-Dist: x-transformers >=1.40.3
